<?xml version="1.0" encoding="UTF-8"?><gc:CodeList xmlns:gc="http://docs.oasis-open.org/codelist/ns/genericode/1.0/"><gc:Identification><gc:ShortName></gc:ShortName><gc:LongName></gc:LongName><gc:Version>2021-03-19</gc:Version><gc:CanonicalUri>urn:de:fim:codeliste:gesetzlichervertreterbevollmächtigter</gc:CanonicalUri><gc:CanonicalVersionUri>urn:de:fim:codeliste:gesetzlichervertreterbevollmächtigter_2021-03-19</gc:CanonicalVersionUri></gc:Identification><gc:ColumnSet><gc:Column Id="code" Use="required"><gc:ShortName>Code</gc:ShortName><gc:Data Type="string"/></gc:Column><gc:Column Id="name" Use="required"><gc:ShortName>Name</gc:ShortName><gc:Data Type="string"/></gc:Column><gc:Key Id="codeKey"><gc:ShortName>CodeKey</gc:ShortName><gc:ColumnRef Ref="code"/></gc:Key><gc:Key Id="codenameKey"><gc:ShortName>CodenameKey</gc:ShortName><gc:ColumnRef Ref="name"/></gc:Key></gc:ColumnSet><gc:SimpleCodeList><gc:Row><gc:Value ColumnRef="code"><gc:SimpleValue>001</gc:SimpleValue></gc:Value><gc:Value ColumnRef="name"><gc:SimpleValue>Nein.</gc:SimpleValue></gc:Value></gc:Row><gc:Row><gc:Value ColumnRef="code"><gc:SimpleValue>002</gc:SimpleValue></gc:Value><gc:Value ColumnRef="name"><gc:SimpleValue>Ja, durch eine gesetzliche Vertretung (natürliche Person).</gc:SimpleValue></gc:Value></gc:Row><gc:Row><gc:Value ColumnRef="code"><gc:SimpleValue>003</gc:SimpleValue></gc:Value><gc:Value ColumnRef="name"><gc:SimpleValue>Ja, durch eine gesetzliche Vertretung (juristische Person).</gc:SimpleValue></gc:Value></gc:Row><gc:Row><gc:Value ColumnRef="code"><gc:SimpleValue>004</gc:SimpleValue></gc:Value><gc:Value ColumnRef="name"><gc:SimpleValue>Ja, durch eine bevollmächtigte Person (natürliche Person).</gc:SimpleValue></gc:Value></gc:Row><gc:Row><gc:Value ColumnRef="code"><gc:SimpleValue>005</gc:SimpleValue></gc:Value><gc:Value ColumnRef="name"><gc:SimpleValue>Ja, durch eine bevollmächtigte Person (juristische Person).</gc:SimpleValue></gc:Value></gc:Row></gc:SimpleCodeList></gc:CodeList>